smallparts/__init__.py
smallparts/constants.py
smallparts/namespaces.py
smallparts/pipelines.py
smallparts/sequences.py
smallparts/time_display.py
smallparts/l10n/__init__.py
smallparts/l10n/enumerations.py
smallparts/l10n/languages.py
smallparts/l10n/time_indications.py
smallparts/markup/__init__.py
smallparts/markup/characters.py
smallparts/markup/elements.py
smallparts/markup/generators.py
smallparts/markup/parsers.py
smallparts/text/__init__.py
smallparts/text/join.py
smallparts/text/reduce.py
smallparts/text/split.py
smallparts/text/templates.py
smallparts/text/transcode.py
smallparts/text/translate.py
smallparts-1.0.0.dist-info/LICENSE.txt
smallparts-1.0.0.dist-info/METADATA
smallparts-1.0.0.dist-info/WHEEL
smallparts-1.0.0.dist-info/top_level.txt
smallparts-1.0.0.dist-info/RECORD
