Metadata-Version: 2.1
Name: smallparts
Version: 1.0.0
Summary: A humble collection of convenience modules for use with Python 3
Home-page: https://github.com/blackstream-x/smallparts
Author: Rainer Schwarzbach
Author-email: rainer@blackstream.de
License: UNKNOWN
Project-URL: Documentation, https://blackstream-x.github.io/smallparts/
Project-URL: Source, https://github.com/blackstream-x/smallparts
Project-URL: Tracker, https://github.com/blackstream-x/smallparts/issues
Platform: UNKNOWN
Classifier: Development Status :: 5 - Production/Stable
Classifier: Intended Audience :: Developers
Classifier: Topic :: Software Development :: Libraries
Classifier: Topic :: Text Processing :: General
Classifier: License :: OSI Approved :: MIT License
Classifier: Programming Language :: Python :: 3
Classifier: Programming Language :: Python :: 3.6
Classifier: Programming Language :: Python :: 3.7
Classifier: Programming Language :: Python :: 3.8
Classifier: Programming Language :: Python :: 3.9
Classifier: Programming Language :: Python :: 3 :: Only
Requires-Python: >=3.6
